Metadata-Version: 2.4
Name: amg-player
Version: 2025.12.20.0
Summary: Browse & play embedded tracks from Angry Metal Guy music reviews
Home-page: https://github.com/desbma/amg-player
Download-URL: https://github.com/desbma/amg-player/archive/2025.12.20.0.tar.gz
Author: desbma
Keywords: music,metal,extreme,angry,guy,player,youtube,bandcamp,soundcloud
Classifier: Development Status :: 4 - Beta
Classifier: Environment :: Console
Classifier: Intended Audience :: End Users/Desktop
Classifier: License :: OSI Approved :: GNU General Public License v3 (GPLv3)
Classifier: Operating System :: OS Independent
Classifier: Programming Language :: Python
Classifier: Programming Language :: Python :: 3
Classifier: Programming Language :: Python :: 3 :: Only
Classifier: Topic :: Multimedia :: Sound/Audio :: Players
Classifier: Topic :: Utilities
License-File: LICENSE
Requires-Dist: cssselect>=1.2.0
Requires-Dist: curses-menu==0.5.0
Requires-Dist: lxml>=5.1.0
Requires-Dist: more_itertools>=10.2.0
Requires-Dist: mutagen>=1.47.0
Requires-Dist: Pillow>=10.3.0
Requires-Dist: platformdirs>=4.2.0
Requires-Dist: python-magic>=0.4.27
Requires-Dist: requests>=2.31.0
Requires-Dist: tqdm>=4.66.4
Requires-Dist: unidecode>=1.3.8
Requires-Dist: web_cache>=1.1.0
Requires-Dist: yt-dlp>=2025.12.08
Dynamic: author
Dynamic: classifier
Dynamic: description
Dynamic: description-content-type
Dynamic: download-url
Dynamic: home-page
Dynamic: keywords
Dynamic: license-file
Dynamic: requires-dist
Dynamic: summary
